CHANGES.txt
LICENSE.txt
MANIFEST.in
README.txt
setup.py
js/__init__.py
js.html5shiv.egg-info/PKG-INFO
js.html5shiv.egg-info/SOURCES.txt
js.html5shiv.egg-info/dependency_links.txt
js.html5shiv.egg-info/entry_points.txt
js.html5shiv.egg-info/namespace_packages.txt
js.html5shiv.egg-info/not-zip-safe
js.html5shiv.egg-info/requires.txt
js.html5shiv.egg-info/top_level.txt
js/html5shiv/__init__.py
js/html5shiv/test_html5shiv.txt
js/html5shiv/resources/html5shiv-printshiv.js
js/html5shiv/resources/html5shiv.js