Metadata-Version: 1.0
Name: js.html5shiv
Version: 3.5
Summary: Fanstatic packaging of html5shiv
Home-page: UNKNOWN
Author: Fanstatic Developers
Author-email: fanstatic@googlegroups.com
License: BSD
Platform: UNKNOWN
